infrared_rally-3.0.0.dist-info/DESCRIPTION.rst
infrared_rally-3.0.0.dist-info/METADATA
infrared_rally-3.0.0.dist-info/RECORD
infrared_rally-3.0.0.dist-info/WHEEL
infrared_rally-3.0.0.dist-info/entry_points.txt
infrared_rally-3.0.0.dist-info/metadata.json
infrared_rally-3.0.0.dist-info/pbr.json
infrared_rally-3.0.0.dist-info/top_level.txt
rally/__init__.py
rally/main.yml
rally/plugin.spec
rally/filter_plugins/try_default.py
rally/tasks/run.yml
rally/tasks/post/report.yml
rally/tasks/pre/main.yml
rally/tasks/setup/main.yml
rally/tasks/setup/git/main.yml
rally/tasks/setup/rpm/install_plugins_source.yml
rally/tasks/setup/rpm/main.yml
rally/vars/image/cirros.yml
rally/vars/setup/git.yml
rally/vars/setup/rpm.yml
rally/vars/tests/ceilometer-gate.yml
rally/vars/tests/cinder-gate.yml
rally/vars/tests/cinder-rally.yml
rally/vars/tests/cisco.yml
rally/vars/tests/designate-gate.yml
rally/vars/tests/designate-rally.yml
rally/vars/tests/glance-gate.yml
rally/vars/tests/heat-rally.yml
rally/vars/tests/keystone-gate.yml
rally/vars/tests/manila-rally.yml
rally/vars/tests/minimal.yml
rally/vars/tests/network.yml
rally/vars/tests/neutron-gate.yml
rally/vars/tests/neutron-rally.yml
rally/vars/tests/none.yml
rally/vars/tests/nova-ec2.yml
rally/vars/tests/nova-rally.yml
rally/vars/tests/odl.yml
rally/vars/tests/sahara-rally.yml
rally/vars/tests/security-groups-basic.yml
rally/vars/tests/security-groups.yml
rally/vars/tests/swift-dummy.yml
rally/vars/tests/trove-dummy.yml
